crowpy/__init__.py
crowpy/crowpy.py
crowpy/driver.py
crowpy/usps.py
crowpy-0.1.1.dist-info/LICENSE
crowpy-0.1.1.dist-info/METADATA
crowpy-0.1.1.dist-info/WHEEL
crowpy-0.1.1.dist-info/top_level.txt
crowpy-0.1.1.dist-info/RECORD
