Metadata-Version: 2.1
Name: crowpy
Version: 0.1.1
Summary: Python code for calculating travel distance of USPS shipments
Home-page: https://github.com/jcapili/crowpy
Author: Jason Capili
Author-email: jcapili@alumni.scu.edu
License: MIT
Keywords: usps shipping carbon offsets miles
Platform: UNKNOWN
Classifier: Development Status :: 4 - Beta
Classifier: Operating System :: MacOS :: MacOS X
Classifier: Intended Audience :: Developers
Classifier: License :: OSI Approved :: MIT License
Classifier: Natural Language :: English
Classifier: Programming Language :: Python
Classifier: Topic :: Software Development :: Libraries :: Python Modules
Classifier: Topic :: Software Development :: Testing
Requires-Dist: requests
Requires-Dist: tqdm
Requires-Dist: geopy
Requires-Dist: xmltodict
Requires-Dist: lxml
